checkitbaby/__init__.py
checkitbaby/agent.py
checkitbaby/checkitbaby.py
checkitbaby/feedback.py
checkitbaby/fortigate_agent.py
checkitbaby/fortigate_agent_bfd.py
checkitbaby/fortigate_agent_execute.py
checkitbaby/fortigate_agent_ha.py
checkitbaby/fortigate_agent_ipsec.py
checkitbaby/fortigate_agent_multicast.py
checkitbaby/fortigate_agent_route.py
checkitbaby/fortigate_agent_sdwan.py
checkitbaby/fortigate_agent_session.py
checkitbaby/fortigate_agent_system.py
checkitbaby/fortipoc_agent.py
checkitbaby/fortiswitch_agent.py
checkitbaby/lxc_agent.py
checkitbaby/playbook.py
checkitbaby/run_playbook.py
checkitbaby/testcase.py
checkitbaby/vyos_agent.py
checkitbaby-1.8.dist-info/LICENSE
checkitbaby-1.8.dist-info/METADATA
checkitbaby-1.8.dist-info/WHEEL
checkitbaby-1.8.dist-info/top_level.txt
checkitbaby-1.8.dist-info/RECORD
